epython/__init__.py
epython/blackscholes.py
epython/cython_backend.py
epython/epython.py
epython-0.0.5.dist-info/LICENSE
epython-0.0.5.dist-info/METADATA
epython-0.0.5.dist-info/WHEEL
epython-0.0.5.dist-info/entry_points.txt
epython-0.0.5.dist-info/top_level.txt
epython-0.0.5.dist-info/RECORD
